.coveragerc
.gitattributes
.pylintrc
.travis.yml
AUTHORS
ChangeLog
LICENSE
MANIFEST.in
Makefile
README.md
pytest.ini
requirements.txt
setup.cfg
setup.py
tox.ini
doc/advanced_usage.rst
doc/api.rst
doc/builtin_plugins.rst
doc/changelog.rst
doc/conf.py
doc/config_doc.py
doc/configuration.rst
doc/cookbook.rst
doc/customizing_slash.rst
doc/details.rst
doc/development.rst
doc/errors.rst
doc/faq.rst
doc/features.rst
doc/fixtures.rst
doc/hook_list_doc.py
doc/hooks.rst
doc/index.rst
doc/internals.rst
doc/logging.rst
doc/parallel.rst
doc/parameters.rst
doc/pip_requirements.txt
doc/plugins.rst
doc/slash_run.rst
doc/tags.rst
doc/tour.rst
doc/transparent.png
doc/unit_testing.rst
doc/warnings.rst
doc/_static/slash-logo.png
scripts/build_test_dir.py
scripts/make_release.py
slash/__init__.py
slash/__version__.py
slash/_compat.py
slash/app.py
slash/assertions.py
slash/cleanups.py
slash/conf.py
slash/ctx.py
slash/exception_handling.py
slash/exceptions.py
slash/exthook.py
slash/hooks.py
slash/interfaces.py
slash/loader.py
slash/log.py
slash/resuming.py
slash/runner.py
slash/site.py
slash/warnings.py
slash/core/__init__.py
slash/core/cleanup_manager.py
slash/core/details.py
slash/core/error.py
slash/core/exclusions.py
slash/core/function_test.py
slash/core/local_config.py
slash/core/markers.py
slash/core/metadata.py
slash/core/requirements.py
slash/core/result.py
slash/core/runnable_test.py
slash/core/runnable_test_factory.py
slash/core/scope_manager.py
slash/core/session.py
slash/core/tagging.py
slash/core/test.py
slash/core/variation.py
slash/core/variation_factory.py
slash/core/fixtures/__init__.py
slash/core/fixtures/active_fixture.py
slash/core/fixtures/fixture.py
slash/core/fixtures/fixture_base.py
slash/core/fixtures/fixture_store.py
slash/core/fixtures/namespace.py
slash/core/fixtures/parameters.py
slash/core/fixtures/utils.py
slash/ext/__init__.py
slash/frontend/__init__.py
slash/frontend/list_config.py
slash/frontend/main.py
slash/frontend/slash_list.py
unnamed998736.egg-info/PKG-INFO
unnamed998736.egg-info/SOURCES.txt
unnamed998736.egg-info/dependency_links.txt
unnamed998736.egg-info/entry_points.txt
unnamed998736.egg-info/not-zip-safe
unnamed998736.egg-info/pbr.json
unnamed998736.egg-info/requires.txt
unnamed998736.egg-info/top_level.txt