Metadata-Version: 2.1
Name: unnamed998736
Version: 1.6.2.dev9
Summary: A Modern Testing Framework for Large-scale Projects
Home-page: http://getslash.github.io/
Author: Rotem Yaari
Author-email: vmalloc@gmail.com
License: BSD
Platform: UNKNOWN
Classifier: Programming Language :: Python :: 2.7
Classifier: Programming Language :: Python :: 3.5
Classifier: Programming Language :: Python :: 3.6
Provides-Extra: doc
Provides-Extra: testing
